pycryptosat.pypy310-pp73-darwin.so
msvc/stdint.h
picosat/picosat.c
picosat/pico_config.h
picosat/version.c
picosat/picosat.h
oracle/utils.h
oracle/oracle.h
oracle/oracle.cpp
pycryptosat-5.11.21.dist-info/RECORD
pycryptosat-5.11.21.dist-info/AUTHORS
pycryptosat-5.11.21.dist-info/WHEEL
pycryptosat-5.11.21.dist-info/top_level.txt
pycryptosat-5.11.21.dist-info/LICENSE.txt
pycryptosat-5.11.21.dist-info/METADATA
