Metadata-Version: 2.1
Name: pycryptosat
Version: 5.11.21
Summary: Bindings to CryptoMiniSat, an advanced SAT solver
Home-page: https://github.com/msoos/cryptominisat
Author-email: Mate Soos <soos.mate@gmail.com>
Maintainer-email: Mate Soos <soos.mate@gmail.com>
License: Copyright (C) 2009-2020 Authors of CryptoMiniSat, see AUTHORS file
Keywords: sat,cryptography
Classifier: Development Status :: 4 - Beta
Classifier: Intended Audience :: Developers
Classifier: Operating System :: OS Independent
Classifier: Programming Language :: C++
Classifier: Programming Language :: Python :: 3
Classifier: Programming Language :: Python :: 3.5
Classifier: License :: OSI Approved :: MIT License
Classifier: Topic :: Utilities
Requires-Python: >=3.5
License-File: LICENSE.txt
License-File: AUTHORS
